moresque/__init__.py
moresque/assessment.py
moresque/ensembles.py
moresque/propagation.py
moresque/propagator_sim.py
moresque/stat_output.py
moresque/uqm.py
moresque/ustructures.py
MoReSQUE-1.0.dist-info/METADATA
MoReSQUE-1.0.dist-info/WHEEL
MoReSQUE-1.0.dist-info/entry_points.txt
MoReSQUE-1.0.dist-info/top_level.txt
MoReSQUE-1.0.dist-info/RECORD
