Metadata-Version: 2.1
Name: MoReSQUE
Version: 1.0
Summary: Uncertainty quantification module for mosaik
Home-page: UNKNOWN
Author: Cornelius Steinbrink
Author-email: mosaik@offis.de
License: UNKNOWN
Platform: UNKNOWN
Classifier: Topic :: Scientific/Engineering
Classifier: License :: OSI Approved :: MIT License
Classifier: Operating System :: OS Independent
Classifier: Intended Audience :: Science/Research
Classifier: Programming Language :: Python :: 3
Classifier: Programming Language :: Python :: 3.8
Classifier: Programming Language :: Python :: 3.9
Classifier: Natural Language :: English
Classifier: Programming Language :: Python
Requires-Dist: mosaik-api (>=2.0)
Requires-Dist: numpy
Requires-Dist: scipy
Requires-Dist: pyDOE
Requires-Dist: arrow
Requires-Dist: statsmodels
